jetblack_rabbitmqmon/__init__.py
jetblack_rabbitmqmon/api.py
jetblack_rabbitmqmon/channel.py
jetblack_rabbitmqmon/clients/__init__.py
jetblack_rabbitmqmon/clients/aiohttp_requester.py
jetblack_rabbitmqmon/clients/bareclient_requester.py
jetblack_rabbitmqmon/connection.py
jetblack_rabbitmqmon/message.py
jetblack_rabbitmqmon/monitor.py
jetblack_rabbitmqmon/node.py
jetblack_rabbitmqmon/requester.py
jetblack_rabbitmqmon/user.py
jetblack_rabbitmqmon/version.py
jetblack_rabbitmqmon/vhost.py
jetblack_rabbitmqmon/vhost_binding.py
jetblack_rabbitmqmon/vhost_exchange.py
jetblack_rabbitmqmon/vhost_queue.py
jetblack_rabbitmqmon-2.0.0.dist-info/WHEEL
jetblack_rabbitmqmon-2.0.0.dist-info/METADATA
jetblack_rabbitmqmon-2.0.0.dist-info/RECORD
