Metadata-Version: 2.1
Name: jetblack-rabbitmqmon
Version: 2.0.0
Summary: RabbitMQ Monitor
Home-page: https://github.com/rob-blackbourn/jetblack-rabbitmqmon
License: Apache-2.0
Author: Rob Blackbourn
Author-email: rob.blackbourn@gmail.com
Requires-Python: >=3.7,<4.0
Classifier: License :: OSI Approved :: Apache Software License
Classifier: Programming Language :: Python :: 3
Classifier: Programming Language :: Python :: 3.7
Classifier: Programming Language :: Python :: 3.8
Provides-Extra: aiohttp
Provides-Extra: bareclient
Requires-Dist: aiohttp (>=3.6.2,<4.0.0); extra == "aiohttp"
Requires-Dist: bareclient (>=4.0.1,<5.0.0); extra == "bareclient"
Project-URL: Repository, https://github.com/rob-blackbourn/jetblack-rabbitmqmon
